flask_filer/__about__.py
flask_filer/__init__.py
flask_filer/api.py
flask_filer/exceptions.py
flask_filer/utils.py
flask_filer-0.1.1.dist-info/LICENSE
flask_filer-0.1.1.dist-info/METADATA
flask_filer-0.1.1.dist-info/WHEEL
flask_filer-0.1.1.dist-info/top_level.txt
flask_filer-0.1.1.dist-info/RECORD
